gits/__init__.py
gits/_main.py
gangneung_its-1.0.0.dist-info/METADATA
gangneung_its-1.0.0.dist-info/WHEEL
gangneung_its-1.0.0.dist-info/top_level.txt
gangneung_its-1.0.0.dist-info/RECORD
