Metadata-Version: 2.4
Name: gangneung-its
Version: 1.0.0
Summary: 강릉 ITS API를 파이썬에서 쉽게 사용할 수 있게 해 주는 라이브러리입니다.
Author-email: 이우진 <hihiohak@gmail.com>
License: MIT
Project-URL: Homepage, https://github.com/Drbrain0620/gangneung-its
Project-URL: Issues, https://github.com/Drbrain0620/gangneung-its/issues
Requires-Python: >=3.8
Requires-Dist: requests
Requires-Dist: tenacity
